async_kernel/__init__.py
async_kernel/__main__.py
async_kernel/asyncshell.py
async_kernel/caller.py
async_kernel/comm.py
async_kernel/command.py
async_kernel/common.py
async_kernel/compiler.py
async_kernel/debugger.py
async_kernel/iostream.py
async_kernel/kernel.py
async_kernel/kernelspec.py
async_kernel/pending.py
async_kernel/py.typed
async_kernel/typing.py
async_kernel/utils.py
async_kernel/interface/__init__.py
async_kernel/interface/base.py
async_kernel/interface/callable.py
async_kernel/interface/zmq.py
async_kernel/resources/logo-32x32.png
async_kernel/resources/logo-64x64.png
async_kernel/resources/logo-svg.svg
async_kernel-0.12.0.data/data/share/jupyter/kernels/async/kernel.json
async_kernel-0.12.0.data/data/share/jupyter/kernels/async/logo-32x32.png
async_kernel-0.12.0.data/data/share/jupyter/kernels/async/logo-64x64.png
async_kernel-0.12.0.data/data/share/jupyter/kernels/async/logo-svg.svg
async_kernel-0.12.0.dist-info/METADATA
async_kernel-0.12.0.dist-info/WHEEL
async_kernel-0.12.0.dist-info/entry_points.txt
async_kernel-0.12.0.dist-info/licenses/IPYTHON_LICENSE
async_kernel-0.12.0.dist-info/licenses/LICENSE
async_kernel-0.12.0.dist-info/RECORD
