Metadata-Version: 2.4
Name: async-kernel
Version: 0.12.0
Summary: A concurrent python kernel for Jupyter supporting AnyIO, AsyncIO and Trio.
Project-URL: Homepage, https://fleming79.github.io/async-kernel
Project-URL: Documentation, https://fleming79.github.io/async-kernel
Project-URL: Source, https://github.com/fleming79/async-kernel
Project-URL: Tracker, https://github.com/fleming79/async-kernel/issues
Project-URL: Changelog, https://fleming79.github.io/async-kernel/latest/about/changelog/
Author-email: Alan Fleming <async-python@proton.me>
License-Expression: MIT
License-File: IPYTHON_LICENSE
License-File: LICENSE
Keywords: Interactive,Interpreter,Jupyter,Shell,Web
Classifier: Development Status :: 4 - Beta
Classifier: Framework :: AnyIO
Classifier: Framework :: AsyncIO
Classifier: Framework :: Jupyter
Classifier: Framework :: Jupyter :: JupyterLab
Classifier: Framework :: Jupyter :: JupyterLab :: 4
Classifier: Framework :: Jupyter :: JupyterLab :: Extensions
Classifier: Framework :: Jupyter :: JupyterLab :: Extensions :: Prebuilt
Classifier: Framework :: Trio
Classifier: Intended Audience :: Developers
Classifier: Intended Audience :: Science/Research
Classifier: Intended Audience :: System Administrators
Classifier: Programming Language :: Python
Classifier: Programming Language :: Python :: 3.11
Classifier: Programming Language :: Python :: 3.12
Classifier: Programming Language :: Python :: 3.13
Classifier: Programming Language :: Python :: 3.14
Classifier: Typing :: Typed
Requires-Python: >=3.11
Requires-Dist: aiologic>=0.16.0
Requires-Dist: anyio>=4.12
Requires-Dist: comm>=0.2
Requires-Dist: ipython>=9.0
Requires-Dist: jupyter-client>=8.8; sys_platform != 'emscripten'
Requires-Dist: jupyter-core>=5.9.1
Requires-Dist: matplotlib-inline>0.1
Requires-Dist: orjson>=3.10.16
Requires-Dist: pyzmq>=27.0; sys_platform != 'emscripten'
Requires-Dist: traitlets>=5.14
Requires-Dist: typing-extensions>=4.14
Requires-Dist: wrapt>=2.0.1
